setup.py
pyconv/__init__.py
pyconv/addmenu.py
pyconv/core.py
pyconv.egg-info/PKG-INFO
pyconv.egg-info/SOURCES.txt
pyconv.egg-info/dependency_links.txt
pyconv.egg-info/entry_points.txt
pyconv.egg-info/requires.txt
pyconv.egg-info/top_level.txt