Metadata-Version: 1.0
Name: pyconv
Version: 0.2
Summary: Text file code conversion Tool
Home-page: http://github.com/reorx/pyconv
Author: reorx
Author-email: novoreorx@gmail.com
License: License :: OSI Approved :: MIT License
Platform: UNKNOWN
